{
"type":"FeatureCollection",
"features":[

{
"type":"Feature",
"properties":{
"title":"Baustelle B239 Herford",
"type":"baustelle"
},
"geometry":{
"type":"Point",
"coordinates":[8.672,52.114]
}
},

{
"type":"Feature",
"properties":{
"title":"Unfall A30 Bünde",
"type":"unfall"
},
"geometry":{
"type":"Point",
"coordinates":[8.598,52.198]
}
}

]
}
